{
  "contacts": [
    {
      "id": "1ff2",
      "name": "Nova Sessão",
      "email": "heduardocr7@gmail.com",
      "phone": "(84) 99836-0157",
      "address": "Rua Manoel Aires, 37, Centro",
      "birthday": "2002-06-20"
    },
    {
      "id": "03fd",
      "name": "AAAAAAAAEEEEEIOOOOUUUUU",
      "email": "heduardocr7@gmail.com",
      "phone": "(84) 99836-0157",
      "address": "Rua Manoel Aires, 37, Centro",
      "birthday": "2002-06-20"
    },
    {
      "id": "f650",
      "name": "Nova Sessão",
      "email": "heduardocr7@gmail.com",
      "phone": "(84) 99836-0157",
      "address": "",
      "birthday": "2025-06-18"
    },
    {
      "id": "4196",
      "name": "Aaron Paul",
      "email": "heduardocr7@gmail.com",
      "phone": "(84) 99836-0157",
      "address": "",
      "birthday": "2025-06-14"
    },
    {
      "id": "7ca4",
      "name": "Aaron Paul",
      "email": "heduardocr7@gmail.com",
      "phone": "(84) 99836-0157",
      "address": "",
      "birthday": "2025-06-19"
    },
    {
      "id": "e930",
      "name": "AAAAAAAAAABBBBBCCCCC",
      "email": "heduardocr7@gmail.com",
      "phone": "(84) 99836-0157",
      "address": "",
      "birthday": "2025-06-19"
    },
    {
      "id": "f51e",
      "name": "Lucas",
      "email": "lucas2@email.com",
      "phone": "84989987845",
      "address": "Avenida Erivan França",
      "birthday": "2000-07-08"
    },
    {
      "id": "8247",
      "name": "TOCANOCALLERIQUEÉGOL",
      "email": "heduardocr7@gmail.com",
      "phone": "(84) 99836-0157",
      "address": "Rua Manoel Aires, 37, Centro",
      "birthday": "2002-06-20"
    }
  ]
}